asapp/desktop.jinja2
asapp/main.py
asapp-0.1.1.dist-info/entry_points.txt
asapp-0.1.1.dist-info/WHEEL
asapp-0.1.1.dist-info/METADATA
asapp-0.1.1.dist-info/RECORD
